aiotestspeed/__init__.py
aiotestspeed/__main__.py
aiotestspeed/aio.py
aiotestspeed/cli.py
aiotestspeed/version.py
aiotestspeed-0.0.1.dist-info/LICENSE
aiotestspeed-0.0.1.dist-info/METADATA
aiotestspeed-0.0.1.dist-info/WHEEL
aiotestspeed-0.0.1.dist-info/top_level.txt
aiotestspeed-0.0.1.dist-info/RECORD
