Metadata-Version: 2.1
Name: aiotestspeed
Version: 0.0.1
Summary: Asynchronous python library to test connection speed, based on the speedtest project.
Home-page: https://github.com/py-paulo/aiotestspeed.git
Author: Paulo Roberto <paulo.rb.beserra@gmail.com>
Author-email: paulo.rb.beserra@gmail.com
License: MIT
Project-URL: GitHub: issues, https://github.com/py-paulo/aiotestspeed/issues
Project-URL: GitHub: repo, https://github.com/py-paulo/aiotestspeed
Keywords: aio,python,asyncio,test,io,speed
Platform: UNKNOWN
Classifier: Environment :: Console
Classifier: Programming Language :: Python :: 3.6
Classifier: Programming Language :: Python :: 3.7
Classifier: Programming Language :: Python :: 3.8
Classifier: Operating System :: POSIX
Classifier: Operating System :: MacOS :: MacOS X
Classifier: Operating System :: Microsoft :: Windows
Classifier: Framework :: AsyncIO
Provides: aiotestspeed
Requires-Python: >=3.6
Requires-Dist: click (~=7.1.2)
